LICENSE
MANIFEST.in
README.md
setup.py
mycelya_torch/__init__.py
mycelya_torch/_backend_hooks.py
mycelya_torch/_client_manager.py
mycelya_torch/_device.py
mycelya_torch/_logging.py
mycelya_torch/_machine.py
mycelya_torch/_orchestrator.py
mycelya_torch/_package_version.py
mycelya_torch/_pickle.py
mycelya_torch/_remote.py
mycelya_torch/_storage.py
mycelya_torch/_utils.py
mycelya_torch.egg-info/PKG-INFO
mycelya_torch.egg-info/SOURCES.txt
mycelya_torch.egg-info/dependency_links.txt
mycelya_torch.egg-info/requires.txt
mycelya_torch.egg-info/top_level.txt
mycelya_torch/aten/__init__.py
mycelya_torch/aten/copy.py
mycelya_torch/aten/dispatch.py
mycelya_torch/aten/scalar.py
mycelya_torch/clients/__init__.py
mycelya_torch/clients/base_client.py
mycelya_torch/clients/mock/__init__.py
mycelya_torch/clients/mock/client.py
mycelya_torch/clients/modal/__init__.py
mycelya_torch/clients/modal/client.py
mycelya_torch/csrc/Mycelya.h
mycelya_torch/csrc/MycelyaAllocator.cpp
mycelya_torch/csrc/MycelyaAllocator.h
mycelya_torch/csrc/MycelyaHooks.cpp
mycelya_torch/csrc/MycelyaMem.cpp
mycelya_torch/csrc/MycelyaStorageImpl.cpp
mycelya_torch/csrc/MycelyaStorageImpl.h
mycelya_torch/csrc/MycelyaTensorImpl.cpp
mycelya_torch/csrc/MycelyaTensorImpl.h
mycelya_torch/csrc/mycelya_extension.cpp
mycelya_torch/servers/__init__.py
mycelya_torch/servers/mock/__init__.py
mycelya_torch/servers/mock/server.py
mycelya_torch/servers/modal/__init__.py
mycelya_torch/servers/modal/server.py