Metadata-Version: 2.4
Name: mycelya_torch
Version: 0.1.7
Summary: Mycelya: PyTorch extension for transparent remote GPU execution on cloud infrastructure
Home-page: https://github.com/alyxya/mycelya-torch
Author: Mycelya Extension
License: AGPL-3.0-or-later
Classifier: Development Status :: 4 - Beta
Classifier: Intended Audience :: Developers
Classifier: Programming Language :: Python :: 3
Classifier: Programming Language :: Python :: 3.10
Classifier: Programming Language :: Python :: 3.11
Classifier: Programming Language :: Python :: 3.12
Classifier: Programming Language :: Python :: 3.13
Classifier: Topic :: Scientific/Engineering :: Artificial Intelligence
Requires-Python: >=3.10
License-File: LICENSE
Requires-Dist: modal>=1.1.0
Requires-Dist: numpy
Requires-Dist: cloudpickle>=3.1.1
Provides-Extra: aws
Requires-Dist: boto3>=1.33.0; extra == "aws"
Provides-Extra: all
Requires-Dist: boto3>=1.33.0; extra == "all"
Dynamic: author
Dynamic: classifier
Dynamic: description
Dynamic: description-content-type
Dynamic: home-page
Dynamic: license
Dynamic: license-file
Dynamic: provides-extra
Dynamic: requires-dist
Dynamic: requires-python
Dynamic: summary
